spritegen/__init__.py
spritegen/main.py
spritegen-0.1.0.dist-info/METADATA
spritegen-0.1.0.dist-info/WHEEL
spritegen-0.1.0.dist-info/entry_points.txt
spritegen-0.1.0.dist-info/top_level.txt
spritegen-0.1.0.dist-info/RECORD
