Metadata-Version: 2.1
Name: spritegen
Version: 0.1.0
Summary: A tool for generating placeholder spritesheets
Home-page: https://github.com/demestav/spritegen
Author: Demetris Stavrou
Classifier: Programming Language :: Python :: 3
Requires-Dist: pillow
